nubium_schema_utils/__init__.py
nubium_schema_utils/schema_make_avsc.py
nubium_schema_utils/utils.py
nubium_schemas/__init__.py
nubium_schemas/campaign_response/__init__.py
nubium_schemas/campaign_response/schema_components.py
nubium_schemas/campaign_response/schemas.py
nubium_schemas/nubium_integrations/__init__.py
nubium_schemas/nubium_integrations/azure/__init__.py
nubium_schemas/nubium_integrations/azure/schema_components.py
nubium_schemas/nubium_integrations/azure/schemas.py
nubium_schemas/nubium_integrations/drift/__init__.py
nubium_schemas/nubium_integrations/drift/schema_components.py
nubium_schemas/nubium_integrations/drift/schemas.py
nubium_schemas/nubium_integrations/dynamic_form/__init__.py
nubium_schemas/nubium_integrations/dynamic_form/schema_components.py
nubium_schemas/nubium_integrations/dynamic_form/schemas.py
nubium_schemas/nubium_integrations/eloqua/__init__.py
nubium_schemas/nubium_integrations/eloqua/schema_components.py
nubium_schemas/nubium_integrations/eloqua/schemas.py
nubium_schemas/nubium_integrations/outreach/__init__.py
nubium_schemas/nubium_integrations/outreach/schema_components.py
nubium_schemas/nubium_integrations/outreach/schemas.py
nubium_schemas/nubium_integrations/partner/__init__.py
nubium_schemas/nubium_integrations/partner/schema_components.py
nubium_schemas/nubium_integrations/partner/schemas.py
nubium_schemas/nubium_integrations/salesforce/__init__.py
nubium_schemas/nubium_integrations/salesforce/schema_components.py
nubium_schemas/nubium_integrations/salesforce/schemas.py
nubium_schemas/nubium_shared_apps/__init__.py
nubium_schemas/nubium_shared_apps/eloqua/__init__.py
nubium_schemas/nubium_shared_apps/eloqua/schema_components.py
nubium_schemas/nubium_shared_apps/eloqua/schemas.py
nubium_schemas/nubium_shared_apps/mode/__init__.py
nubium_schemas/nubium_shared_apps/mode/schema_components.py
nubium_schemas/nubium_shared_apps/mode/schemas.py
nubium_schemas/path_factory/__init__.py
nubium_schemas-2.0.0.dist-info/METADATA
nubium_schemas-2.0.0.dist-info/WHEEL
nubium_schemas-2.0.0.dist-info/top_level.txt
nubium_schemas-2.0.0.dist-info/RECORD
