Metadata-Version: 2.1
Name: nubium-schemas
Version: 2.0.0
Summary: Python dictionary representations of Avro Schema for the nubium project
Home-page: https://gitlab.corp.redhat.com/mkt-ops-de/nubium-schemas.git
Author: Edward Brennan
Author-email: ebrennan@redhat.com
Maintainer: Pramod Toraskar
Maintainer-email: ptoraska@redhat.com
Classifier: Programming Language :: Python :: 3
Classifier: License :: OSI Approved :: MIT License
Classifier: Operating System :: OS Independent
Requires-Dist: dataclasses-avroschema (>=0.20.2)
Requires-Dist: pydantic
Provides-Extra: dev
Requires-Dist: black ; extra == 'dev'
Requires-Dist: pip-tools ; extra == 'dev'
Requires-Dist: pytest ; extra == 'dev'
Requires-Dist: pytest-cov ; extra == 'dev'
Requires-Dist: setuptools-scm ; extra == 'dev'
